combidate/__init__.py
combidate/classes/__init__.py
combidate/classes/case.py
combidate/classes/combination.py
combidate/classes/data_generator.py
combidate/classes/process.py
combidate/processes/__init__.py
combidate/processes/combine.py
combidate/processes/form.py
combidate/processes/genetate.py
combidate-0.1.1.dist-info/LICENSE
combidate-0.1.1.dist-info/METADATA
combidate-0.1.1.dist-info/WHEEL
combidate-0.1.1.dist-info/top_level.txt
combidate-0.1.1.dist-info/RECORD
