Metadata-Version: 2.1
Name: combidate
Version: 0.1.1
Summary: Package for random data generation, combination and data prepare for tests
Home-page: https://github.com/Warrfie/combidate
Author: Kuklikov Maxim (Warrfie)
Author-email: "MaximKuklikov(Warrfie)" <warrfie@gmail.com>
Project-URL: Homepage, https://github.com/Warrfie/combidate
Keywords: QA,SET,random data generation,testing API,testing,autotesting
Classifier: Development Status :: 3 - Alpha
Classifier: Intended Audience :: Information Technology
Classifier: Topic :: Software Development :: Quality Assurance
Classifier: License :: OSI Approved :: MIT License
Classifier: Programming Language :: Python :: 3
Requires-Python: >=3.10, <4
License-File: LICENSE
